wordlemini/__init__.py
wordlemini/__main__.py
wordlemini/_cli.py
wordlemini/_config.py
wordlemini/_keyboards.py
wordlemini/_statistics.py
wordlemini/_util.py
wordlemini/py.typed
wordlemini/template.config.json
wordlemini/assets/statisticstyles.tcss
wordlemini/assets/wordlestyles.tcss
wordlemini/assets/corpus/cs.txt
wordlemini/assets/corpus/de.txt
wordlemini/assets/corpus/en.txt
wordlemini/assets/corpus/es.txt
wordlemini/assets/corpus/fr.txt
wordlemini/assets/corpus/it.txt
wordlemini/assets/corpus/nl.txt
wordlemini/assets/corpus/pt.txt
wordlemini/assets/corpus/ru.txt
wordlemini/assets/images/banner.png
wordlemini/assets/images/stats.png
wordlemini/locales/cs/LC_MESSAGES/messages.mo
wordlemini/locales/de/LC_MESSAGES/messages.mo
wordlemini/locales/en/LC_MESSAGES/messages.mo
wordlemini/locales/es/LC_MESSAGES/messages.mo
wordlemini/locales/fr/LC_MESSAGES/messages.mo
wordlemini/locales/it/LC_MESSAGES/messages.mo
wordlemini/locales/nl/LC_MESSAGES/messages.mo
wordlemini/locales/pt/LC_MESSAGES/messages.mo
wordlemini/locales/ru/LC_MESSAGES/messages.mo
wordlemini-0.1.6.dist-info/LICENSE
wordlemini-0.1.6.dist-info/METADATA
wordlemini-0.1.6.dist-info/WHEEL
wordlemini-0.1.6.dist-info/entry_points.txt
wordlemini-0.1.6.dist-info/top_level.txt
wordlemini-0.1.6.dist-info/RECORD
