Metadata-Version: 2.1
Name: wordlemini
Version: 0.1.6
Summary: Wordle in the command-line
Author: Tomas Vana
Project-URL: Homepage, https://github.com/tomasvana10/wordlemini
Project-URL: Repository, https://github.com/tomasvana10/wordlemini
Keywords: wordle,puzzle,command line interface,game
Classifier: Intended Audience :: End Users/Desktop
Classifier: License :: OSI Approved :: MIT License
Classifier: Operating System :: OS Independent
Classifier: Programming Language :: Python
Classifier: Programming Language :: Python :: 3
Classifier: Topic :: Games/Entertainment
License-File: LICENSE
Requires-Dist: textual
Requires-Dist: platformdirs
Requires-Dist: pycountry
